dataqualityreport/__init__.py
dataqualityreport/data_utils.py
dataqualityreport/dataqualityreport.py
dataqualityreport/tabulate.py
dataqualityreport/viz.py
dataqualityreport-0.0.4.dist-info/LICENSE.txt
dataqualityreport-0.0.4.dist-info/WHEEL
dataqualityreport-0.0.4.dist-info/METADATA
dataqualityreport-0.0.4.dist-info/RECORD
