Metadata-Version: 2.1
Name: dataqualityreport
Version: 0.0.4
Summary: Data Quality Report - visual data profiling for python
Keywords: utilities
Author: Devjit Chakravarti
Author-email: devjit.chakravarti@doordash.com
Requires-Python: >=3.7.1,<3.11
Classifier: Programming Language :: Python :: 3
Classifier: Programming Language :: Python :: 3.8
Classifier: Programming Language :: Python :: 3.9
Classifier: Programming Language :: Python :: 3.10
Classifier: Topic :: Software Development :: Libraries :: Python Modules
Requires-Dist: Jinja2 (>=3.1.1,<4.0.0)
Requires-Dist: joblib
Requires-Dist: matplotlib (>=3.5.0,<4.0.0)
Requires-Dist: numpy (>=1.20,<2.0)
Requires-Dist: pandas (>=1.1.5,<2.0.0)
Requires-Dist: pytest (>=7.1.2,<8.0.0)
Requires-Dist: pytest-cov (>=3.0.0,<4.0.0)
